pyseccomp.py
pyseccomp-0.1.2.dist-info/LICENSE
pyseccomp-0.1.2.dist-info/METADATA
pyseccomp-0.1.2.dist-info/WHEEL
pyseccomp-0.1.2.dist-info/top_level.txt
pyseccomp-0.1.2.dist-info/RECORD
