Metadata-Version: 2.1
Name: pyseccomp
Version: 0.1.2
Summary: An interface to libseccomp using ctypes. API compatible with libseccomp's Python bindings.
Home-page: https://github.com/cptpcrd/pyseccomp
License: MIT
Keywords: seccomp,libseccomp
Platform: UNKNOWN
Classifier: License :: OSI Approved :: MIT License
Classifier: Programming Language :: Python :: 3.6
Classifier: Programming Language :: Python :: 3.7
Classifier: Programming Language :: Python :: 3.8
Classifier: Operating System :: POSIX :: Linux
Requires-Python: >=3.6
